{"loss": 4.005563096143305e-05, "timestamp": 1729240338, "checkpoint_dir_name": null, "done": true, "training_iteration": 51, "trial_id": "a4f87c7c", "date": "2024-10-18_10-32-18", "time_this_iter_s": 0.0005855560302734375, "time_total_s": 17.357983589172363, "pid": 1570120, "hostname": "zimmerib", "node_ip": "139.11.222.200", "config": {"training": {"learning_rate": 0.015390620322723383, "gamma_scheduler": 0.9997730422510523}, "model": {"hidden_size_FDE": 53, "n_layers_hidden_FDE": 4, "activation_FDE": "leaky_relu", "alpha": 0.81190050223117}}, "time_since_restore": 17.357983589172363, "iterations_since_restore": 51, "experiment_tag": "801_activation_FDE=leaky_relu,alpha=0.8119,hidden_size_FDE=53,n_layers_hidden_FDE=4,gamma_scheduler=0.9998,learning_rate=0.0154"}